advurl_shortner/__init__.py
advurl_shortner/advurl_shortner.py
advurl_shortner-1.0.3.dist-info/LICENSE.txt
advurl_shortner-1.0.3.dist-info/METADATA
advurl_shortner-1.0.3.dist-info/WHEEL
advurl_shortner-1.0.3.dist-info/top_level.txt
advurl_shortner-1.0.3.dist-info/RECORD
