Metadata-Version: 2.1
Name: advurl_shortner
Version: 1.0.3
Summary: Easy-to-use, powerful python library to help you to shorten urls with advanced options.
Home-page: https://github.com/advUrlShortner/advurl-shortner-python
Author: Paul Jakobski
License: MIT
Keywords: url,shorten,url_shortner,API
Classifier: Intended Audience :: Developers
Classifier: Topic :: Software Development :: Build Tools
Classifier: License :: OSI Approved :: MIT License
Classifier: Programming Language :: Python :: 3
Classifier: Programming Language :: Python :: 3.5
Classifier: Programming Language :: Python :: 3.6
Classifier: Programming Language :: Python :: 3.7
Classifier: Programming Language :: Python :: 3.8
Classifier: Operating System :: OS Independent
Requires-Python: >=3, !=3.0.*, !=3.1.*, !=3.2.*, !=3.3.*, !=3.4.*
License-File: LICENSE.txt
Requires-Dist: requests >=2.23.0
